bandit/__init__.py
bandit/__main__.py
bandit/blacklists/__init__.py
bandit/blacklists/calls.py
bandit/blacklists/imports.py
bandit/blacklists/utils.py
bandit/cli/__init__.py
bandit/cli/baseline.py
bandit/cli/config_generator.py
bandit/cli/main.py
bandit/core/__init__.py
bandit/core/blacklisting.py
bandit/core/config.py
bandit/core/constants.py
bandit/core/context.py
bandit/core/docs_utils.py
bandit/core/extension_loader.py
bandit/core/issue.py
bandit/core/manager.py
bandit/core/meta_ast.py
bandit/core/metrics.py
bandit/core/node_visitor.py
bandit/core/test_properties.py
bandit/core/test_set.py
bandit/core/tester.py
bandit/core/utils.py
bandit/formatters/__init__.py
bandit/formatters/csv.py
bandit/formatters/custom.py
bandit/formatters/html.py
bandit/formatters/json.py
bandit/formatters/sarif.py
bandit/formatters/screen.py
bandit/formatters/text.py
bandit/formatters/utils.py
bandit/formatters/xml.py
bandit/formatters/yaml.py
bandit/plugins/__init__.py
bandit/plugins/app_debug.py
bandit/plugins/asserts.py
bandit/plugins/crypto_request_no_cert_validation.py
bandit/plugins/django_sql_injection.py
bandit/plugins/django_xss.py
bandit/plugins/exec.py
bandit/plugins/general_bad_file_permissions.py
bandit/plugins/general_bind_all_interfaces.py
bandit/plugins/general_hardcoded_password.py
bandit/plugins/general_hardcoded_tmp.py
bandit/plugins/hashlib_insecure_functions.py
bandit/plugins/huggingface_unsafe_download.py
bandit/plugins/injection_paramiko.py
bandit/plugins/injection_shell.py
bandit/plugins/injection_sql.py
bandit/plugins/injection_wildcard.py
bandit/plugins/insecure_ssl_tls.py
bandit/plugins/jinja2_templates.py
bandit/plugins/logging_config_insecure_listen.py
bandit/plugins/mako_templates.py
bandit/plugins/markupsafe_markup_xss.py
bandit/plugins/pytorch_load.py
bandit/plugins/request_without_timeout.py
bandit/plugins/snmp_security_check.py
bandit/plugins/ssh_no_host_key_verification.py
bandit/plugins/tarfile_unsafe_members.py
bandit/plugins/trojansource.py
bandit-1.8.6.dist-info/LICENSE
bandit-1.8.6.dist-info/METADATA
bandit-1.8.6.dist-info/WHEEL
bandit-1.8.6.dist-info/entry_points.txt
bandit-1.8.6.dist-info/pbr.json
bandit-1.8.6.dist-info/top_level.txt
bandit-1.8.6.dist-info/RECORD
