Metadata-Version: 2.1
Name: bandit
Version: 1.8.6
Summary: Security oriented static analyser for python code.
Home-page: https://bandit.readthedocs.io/
Author: PyCQA
Author-email: code-quality@python.org
License: Apache-2.0
Project-URL: Documentation, https://bandit.readthedocs.io/
Project-URL: Release Notes, https://github.com/PyCQA/bandit/releases
Project-URL: Source Code, https://github.com/PyCQA/bandit
Project-URL: Issue Tracker, https://github.com/PyCQA/bandit/issues
Project-URL: Discord, https://discord.gg/qYxpadCgkx
Project-URL: Sponsor, https://psfmember.org/civicrm/contribute/transact/?reset=1&id=42
Platform: UNKNOWN
Classifier: Development Status :: 5 - Production/Stable
Classifier: Environment :: Console
Classifier: Intended Audience :: Information Technology
Classifier: Intended Audience :: System Administrators
Classifier: Intended Audience :: Developers
Classifier: Operating System :: POSIX :: Linux
Classifier: Operating System :: MacOS :: MacOS X
Classifier: Programming Language :: Python
Classifier: Programming Language :: Python :: 3
Classifier: Programming Language :: Python :: 3.9
Classifier: Programming Language :: Python :: 3.10
Classifier: Programming Language :: Python :: 3.11
Classifier: Programming Language :: Python :: 3.12
Classifier: Programming Language :: Python :: 3.13
Classifier: Programming Language :: Python :: 3 :: Only
Classifier: Topic :: Security
Requires-Python: >=3.9
Provides-Extra: yaml
Provides-Extra: toml
Provides-Extra: baseline
Provides-Extra: sarif
Provides-Extra: test
License-File: LICENSE
